geomdl/BSpline.py
geomdl/CPGen.py
geomdl/NURBS.py
geomdl/__init__.py
geomdl/_convert.py
geomdl/_exchange.py
geomdl/_linalg.py
geomdl/_operations.py
geomdl/_tessellate.py
geomdl/_utilities.py
geomdl/_voxelize.py
geomdl/abstract.py
geomdl/compatibility.py
geomdl/construct.py
geomdl/control_points.py
geomdl/convert.py
geomdl/elements.py
geomdl/evaluators.py
geomdl/exceptions.py
geomdl/exchange.py
geomdl/exchange_vtk.py
geomdl/fitting.py
geomdl/freeform.py
geomdl/functools_lru_cache.py
geomdl/helpers.py
geomdl/knotvector.py
geomdl/linalg.py
geomdl/multi.py
geomdl/operations.py
geomdl/ray.py
geomdl/shortcuts.py
geomdl/sweeping.py
geomdl/tessellate.py
geomdl/trimming.py
geomdl/utilities.py
geomdl/vis.py
geomdl/voxelize.py
geomdl/visualization/VisMPL.py
geomdl/visualization/VisPlotly.py
geomdl/visualization/VisVTK.py
geomdl/visualization/__init__.py
geomdl/visualization/vtk_helpers.py
geomdl-5.3.1.dist-info/LICENSE
geomdl-5.3.1.dist-info/METADATA
geomdl-5.3.1.dist-info/WHEEL
geomdl-5.3.1.dist-info/top_level.txt
geomdl-5.3.1.dist-info/RECORD
