Metadata-Version: 1.2
Name: geomdl
Version: 5.3.1
Summary: Object-oriented B-Spline and NURBS evaluation library
Home-page: https://github.com/orbingol/NURBS-Python
Author: Onur Rauf Bingol
Author-email: nurbs-python@googlegroups.com
License: MIT
Project-URL: Documentation, http://nurbs-python.readthedocs.io/
Project-URL: Source, https://github.com/orbingol/NURBS-Python
Project-URL: Tracker, https://github.com/orbingol/NURBS-Python/issues
Keywords: NURBS B-Spline curve surface CAD modeling visualization surface-generator
Platform: UNKNOWN
Classifier: Development Status :: 5 - Production/Stable
Classifier: Intended Audience :: Science/Research
Classifier: License :: OSI Approved :: MIT License
Classifier: Topic :: Scientific/Engineering :: Mathematics
Classifier: Topic :: Scientific/Engineering :: Visualization
Classifier: Operating System :: OS Independent
Classifier: Programming Language :: Python :: 2
Classifier: Programming Language :: Python :: 2.7
Classifier: Programming Language :: Python :: 3
Classifier: Programming Language :: Python :: 3.4
Classifier: Programming Language :: Python :: 3.5
Classifier: Programming Language :: Python :: 3.6
Classifier: Programming Language :: Python :: 3.7
